streamlit_sparrow_labeling/__init__.py
streamlit_sparrow_labeling/processor.py
streamlit_sparrow_labeling/frontend/build/asset-manifest.json
streamlit_sparrow_labeling/frontend/build/index.html
streamlit_sparrow_labeling/frontend/build/precache-manifest.c87c3fa2a6f512fc2099fce7d92aceeb.js
streamlit_sparrow_labeling/frontend/build/service-worker.js
streamlit_sparrow_labeling/frontend/build/static/css/main.41cd645d.chunk.css
streamlit_sparrow_labeling/frontend/build/static/css/main.41cd645d.chunk.css.map
streamlit_sparrow_labeling/frontend/build/static/js/2.2a12cbe3.chunk.js
streamlit_sparrow_labeling/frontend/build/static/js/2.2a12cbe3.chunk.js.LICENSE.txt
streamlit_sparrow_labeling/frontend/build/static/js/2.2a12cbe3.chunk.js.map
streamlit_sparrow_labeling/frontend/build/static/js/main.744b77a8.chunk.js
streamlit_sparrow_labeling/frontend/build/static/js/main.744b77a8.chunk.js.map
streamlit_sparrow_labeling/frontend/build/static/js/runtime-main.b5044f72.js
streamlit_sparrow_labeling/frontend/build/static/js/runtime-main.b5044f72.js.map
streamlit_sparrow_labeling-0.1.1.dist-info/LICENSE
streamlit_sparrow_labeling-0.1.1.dist-info/METADATA
streamlit_sparrow_labeling-0.1.1.dist-info/WHEEL
streamlit_sparrow_labeling-0.1.1.dist-info/top_level.txt
streamlit_sparrow_labeling-0.1.1.dist-info/RECORD
