Metadata-Version: 2.1
Name: streamlit-sparrow-labeling
Version: 0.1.1
Summary: Streamlit component for invoice document labeling
Home-page: https://github.com/katanaml/streamlit-sparrow-labeling-comp
Author: Andrej Baranovskij
Author-email: andrejus.baranovskis@gmail.com
License: UNKNOWN
Platform: UNKNOWN
Requires-Python: >=3.8
License-File: LICENSE
Requires-Dist: streamlit (>=1.15)
Requires-Dist: streamlit-nested-layout
Requires-Dist: streamlit-javascript
